anywidget/__init__.py
anywidget/_cellmagic.py
anywidget/_descriptor.py
anywidget/_file_contents.py
anywidget/_protocols.py
anywidget/_util.py
anywidget/_version.py
anywidget/experimental.py
anywidget/py.typed
anywidget/widget.py
anywidget/labextension/package.json
anywidget/labextension/static/241.8f42e1b1.js
anywidget/labextension/static/241.8f42e1b1.js.map
anywidget/labextension/static/92.37240556.js
anywidget/labextension/static/92.37240556.js.map
anywidget/labextension/static/main.e16e1493.js
anywidget/labextension/static/main.e16e1493.js.map
anywidget/labextension/static/remoteEntry.b548c4fc.js
anywidget/labextension/static/remoteEntry.b548c4fc.js.map
anywidget/nbextension/extension.js
anywidget/nbextension/index.js
anywidget-0.9.20.data/data/share/jupyter/labextensions/anywidget/package.json
anywidget-0.9.20.data/data/share/jupyter/labextensions/anywidget/static/241.8f42e1b1.js
anywidget-0.9.20.data/data/share/jupyter/labextensions/anywidget/static/241.8f42e1b1.js.map
anywidget-0.9.20.data/data/share/jupyter/labextensions/anywidget/static/92.37240556.js
anywidget-0.9.20.data/data/share/jupyter/labextensions/anywidget/static/92.37240556.js.map
anywidget-0.9.20.data/data/share/jupyter/labextensions/anywidget/static/main.e16e1493.js
anywidget-0.9.20.data/data/share/jupyter/labextensions/anywidget/static/main.e16e1493.js.map
anywidget-0.9.20.data/data/share/jupyter/labextensions/anywidget/static/remoteEntry.b548c4fc.js
anywidget-0.9.20.data/data/share/jupyter/labextensions/anywidget/static/remoteEntry.b548c4fc.js.map
anywidget-0.9.20.data/data/share/jupyter/nbextensions/anywidget/extension.js
anywidget-0.9.20.data/data/share/jupyter/nbextensions/anywidget/index.js
anywidget-0.9.20.data/data/etc/jupyter/nbconfig/notebook.d/anywidget.json
anywidget-0.9.20.dist-info/METADATA
anywidget-0.9.20.dist-info/WHEEL
anywidget-0.9.20.dist-info/licenses/LICENSE
anywidget-0.9.20.dist-info/RECORD
